parallelic/__init__.py
parallelic/__main__.py
parallelic/manager/__init__.py
parallelic/manager/distrib.py
parallelic/runner/__init__.py
parallelic/runner/recv.py
parallelic/util/parser.py
parallelic/util/utils.py
parallelic-0.1.3.dist-info/entry_points.txt
parallelic-0.1.3.dist-info/LICENSE
parallelic-0.1.3.dist-info/WHEEL
parallelic-0.1.3.dist-info/METADATA
parallelic-0.1.3.dist-info/RECORD
