Metadata-Version: 2.1
Name: parallelic
Version: 0.1.3
Summary: Hyper-parallel multi-node task execution engine
Home-page: https://gitlab.com/OnDev-Project/parallelic
License: MPL-2.0
Author: golyalpha
Author-email: golyalpha@gmail.com
Requires-Python: >=3.7,<4.0
Classifier: Development Status :: 1 - Planning
Classifier: License :: OSI Approved
Classifier: Programming Language :: Python :: 3
Classifier: Programming Language :: Python :: 3.7
Requires-Dist: bcrypt (>=3.1,<4.0)
Requires-Dist: cssutils (>=1.0,<2.0)
Requires-Dist: flask (>=1.0,<2.0)
Requires-Dist: flask-assets (>=0.12.0,<0.13.0)
Requires-Dist: flask-compress (>=1.4,<2.0)
Requires-Dist: flask-login (>=0.4.1,<0.5.0)
Requires-Dist: flask-wtf (>=0.14.2,<0.15.0)
Requires-Dist: gunicorn (>=19.9,<20.0)
Requires-Dist: jsmin (>=2.2,<3.0)
Requires-Dist: psycopg2-binary (>=2.7,<3.0)
Requires-Dist: sqlobject (>=3.7,<4.0)
Requires-Dist: toml (>=0.10.0,<0.11.0)
Requires-Dist: udp-filetransfer (>=0.1.2,<0.2.0)
Project-URL: Repository, https://gitlab.com/OnDev-Project/parallelic
